jais/__init__.py
jais/main.py
jais/configs/__init__.py
jais/configs/default.yaml
jais/configs/jais_settings.json
jais/configs/logs.conf
jais/examples/cifar10.py
jais/models/__init__.py
jais/models/example.py
jais/train/__init__.py
jais/train/bs_finder.py
jais/train/log.py
jais/train/losses.py
jais/train/lr_finder.py
jais/train/lr_scheduler.py
jais/train/mixup.py
jais/train/trainer.py
jais/train/tune_hparams.py
jais/utils/__init__.py
jais/utils/fileloader.py
jais/utils/log.py
jais/utils/utils.py
jais/visualize/__init__.py
jais/visualize/data.py
jais/visualize/model.py
jais-0.0.1.18.dist-info/METADATA
jais-0.0.1.18.dist-info/WHEEL
jais-0.0.1.18.dist-info/entry_points.txt
jais-0.0.1.18.dist-info/top_level.txt
jais-0.0.1.18.dist-info/RECORD
